{
  "meta": {
    "name": "Unicode Braille Patterns Reference",
    "block": "U+2800 – U+283F (6-dot patterns, 64 total)",
    "description": "All possible 6-dot braille combinations with their Unicode values, dot patterns, and keyboard chord mappings.",
    "formula": "unicode = 0x2800 + dot1×0x01 + dot2×0x02 + dot3×0x04 + dot4×0x08 + dot5×0x10 + dot6×0x20"
  },
  "keyboard_layout": {
    "description": "Standard Perkins-style keyboard mapping on QWERTY",
    "keys": {
      "F": { "dot": 1, "bit": "0x01", "position": "top-left" },
      "D": { "dot": 2, "bit": "0x02", "position": "mid-left" },
      "S": { "dot": 3, "bit": "0x04", "position": "bottom-left" },
      "J": { "dot": 4, "bit": "0x08", "position": "top-right" },
      "K": { "dot": 5, "bit": "0x10", "position": "mid-right" },
      "L": { "dot": 6, "bit": "0x20", "position": "bottom-right" }
    },
    "modifiers": {
      "Space": "submit / word separator",
      "Backspace": "delete last cell",
      "Enter": "new line"
    }
  },
  "patterns": [
    { "hex": "2800", "dots": [],           "char": "⠀", "decimal": 0,  "binary": "000000" },
    { "hex": "2801", "dots": [1],          "char": "⠁", "decimal": 1,  "binary": "000001" },
    { "hex": "2802", "dots": [2],          "char": "⠂", "decimal": 2,  "binary": "000010" },
    { "hex": "2803", "dots": [1,2],        "char": "⠃", "decimal": 3,  "binary": "000011" },
    { "hex": "2804", "dots": [3],          "char": "⠄", "decimal": 4,  "binary": "000100" },
    { "hex": "2805", "dots": [1,3],        "char": "⠅", "decimal": 5,  "binary": "000101" },
    { "hex": "2806", "dots": [2,3],        "char": "⠆", "decimal": 6,  "binary": "000110" },
    { "hex": "2807", "dots": [1,2,3],      "char": "⠇", "decimal": 7,  "binary": "000111" },
    { "hex": "2808", "dots": [4],          "char": "⠈", "decimal": 8,  "binary": "001000" },
    { "hex": "2809", "dots": [1,4],        "char": "⠉", "decimal": 9,  "binary": "001001" },
    { "hex": "280A", "dots": [2,4],        "char": "⠊", "decimal": 10, "binary": "001010" },
    { "hex": "280B", "dots": [1,2,4],      "char": "⠋", "decimal": 11, "binary": "001011" },
    { "hex": "280C", "dots": [3,4],        "char": "⠌", "decimal": 12, "binary": "001100" },
    { "hex": "280D", "dots": [1,3,4],      "char": "⠍", "decimal": 13, "binary": "001101" },
    { "hex": "280E", "dots": [2,3,4],      "char": "⠎", "decimal": 14, "binary": "001110" },
    { "hex": "280F", "dots": [1,2,3,4],    "char": "⠏", "decimal": 15, "binary": "001111" },
    { "hex": "2810", "dots": [5],          "char": "⠐", "decimal": 16, "binary": "010000" },
    { "hex": "2811", "dots": [1,5],        "char": "⠑", "decimal": 17, "binary": "010001" },
    { "hex": "2812", "dots": [2,5],        "char": "⠒", "decimal": 18, "binary": "010010" },
    { "hex": "2813", "dots": [1,2,5],      "char": "⠓", "decimal": 19, "binary": "010011" },
    { "hex": "2814", "dots": [3,5],        "char": "⠔", "decimal": 20, "binary": "010100" },
    { "hex": "2815", "dots": [1,3,5],      "char": "⠕", "decimal": 21, "binary": "010101" },
    { "hex": "2816", "dots": [2,3,5],      "char": "⠖", "decimal": 22, "binary": "010110" },
    { "hex": "2817", "dots": [1,2,3,5],    "char": "⠗", "decimal": 23, "binary": "010111" },
    { "hex": "2818", "dots": [4,5],        "char": "⠘", "decimal": 24, "binary": "011000" },
    { "hex": "2819", "dots": [1,4,5],      "char": "⠙", "decimal": 25, "binary": "011001" },
    { "hex": "281A", "dots": [2,4,5],      "char": "⠚", "decimal": 26, "binary": "011010" },
    { "hex": "281B", "dots": [1,2,4,5],    "char": "⠛", "decimal": 27, "binary": "011011" },
    { "hex": "281C", "dots": [3,4,5],      "char": "⠜", "decimal": 28, "binary": "011100" },
    { "hex": "281D", "dots": [1,3,4,5],    "char": "⠝", "decimal": 29, "binary": "011101" },
    { "hex": "281E", "dots": [2,3,4,5],    "char": "⠞", "decimal": 30, "binary": "011110" },
    { "hex": "281F", "dots": [1,2,3,4,5],  "char": "⠟", "decimal": 31, "binary": "011111" },
    { "hex": "2820", "dots": [6],          "char": "⠠", "decimal": 32, "binary": "100000" },
    { "hex": "2821", "dots": [1,6],        "char": "⠡", "decimal": 33, "binary": "100001" },
    { "hex": "2822", "dots": [2,6],        "char": "⠢", "decimal": 34, "binary": "100010" },
    { "hex": "2823", "dots": [1,2,6],      "char": "⠣", "decimal": 35, "binary": "100011" },
    { "hex": "2824", "dots": [3,6],        "char": "⠤", "decimal": 36, "binary": "100100" },
    { "hex": "2825", "dots": [1,3,6],      "char": "⠥", "decimal": 37, "binary": "100101" },
    { "hex": "2826", "dots": [2,3,6],      "char": "⠦", "decimal": 38, "binary": "100110" },
    { "hex": "2827", "dots": [1,2,3,6],    "char": "⠧", "decimal": 39, "binary": "100111" },
    { "hex": "2828", "dots": [4,6],        "char": "⠨", "decimal": 40, "binary": "101000" },
    { "hex": "2829", "dots": [1,4,6],      "char": "⠩", "decimal": 41, "binary": "101001" },
    { "hex": "282A", "dots": [2,4,6],      "char": "⠪", "decimal": 42, "binary": "101010" },
    { "hex": "282B", "dots": [1,2,4,6],    "char": "⠫", "decimal": 43, "binary": "101011" },
    { "hex": "282C", "dots": [3,4,6],      "char": "⠬", "decimal": 44, "binary": "101100" },
    { "hex": "282D", "dots": [1,3,4,6],    "char": "⠭", "decimal": 45, "binary": "101101" },
    { "hex": "282E", "dots": [2,3,4,6],    "char": "⠮", "decimal": 46, "binary": "101110" },
    { "hex": "282F", "dots": [1,2,3,4,6],  "char": "⠯", "decimal": 47, "binary": "101111" },
    { "hex": "2830", "dots": [5,6],        "char": "⠰", "decimal": 48, "binary": "110000" },
    { "hex": "2831", "dots": [1,5,6],      "char": "⠱", "decimal": 49, "binary": "110001" },
    { "hex": "2832", "dots": [2,5,6],      "char": "⠲", "decimal": 50, "binary": "110010" },
    { "hex": "2833", "dots": [1,2,5,6],    "char": "⠳", "decimal": 51, "binary": "110011" },
    { "hex": "2834", "dots": [3,5,6],      "char": "⠴", "decimal": 52, "binary": "110100" },
    { "hex": "2835", "dots": [1,3,5,6],    "char": "⠵", "decimal": 53, "binary": "110101" },
    { "hex": "2836", "dots": [2,3,5,6],    "char": "⠶", "decimal": 54, "binary": "110110" },
    { "hex": "2837", "dots": [1,2,3,5,6],  "char": "⠷", "decimal": 55, "binary": "110111" },
    { "hex": "2838", "dots": [4,5,6],      "char": "⠸", "decimal": 56, "binary": "111000" },
    { "hex": "2839", "dots": [1,4,5,6],    "char": "⠹", "decimal": 57, "binary": "111001" },
    { "hex": "283A", "dots": [2,4,5,6],    "char": "⠺", "decimal": 58, "binary": "111010" },
    { "hex": "283B", "dots": [1,2,4,5,6],  "char": "⠻", "decimal": 59, "binary": "111011" },
    { "hex": "283C", "dots": [3,4,5,6],    "char": "⠼", "decimal": 60, "binary": "111100" },
    { "hex": "283D", "dots": [1,3,4,5,6],  "char": "⠽", "decimal": 61, "binary": "111101" },
    { "hex": "283E", "dots": [2,3,4,5,6],  "char": "⠾", "decimal": 62, "binary": "111110" },
    { "hex": "283F", "dots": [1,2,3,4,5,6],"char": "⠿", "decimal": 63, "binary": "111111" }
  ]
}
